pytonik_agent/__init__.py
pytonik_agent/browser.py
pytonik_agent/os.py
pytonik_agent-1.0.5.dist-info/LICENSE.txt
pytonik_agent-1.0.5.dist-info/METADATA
pytonik_agent-1.0.5.dist-info/WHEEL
pytonik_agent-1.0.5.dist-info/top_level.txt
pytonik_agent-1.0.5.dist-info/RECORD
