Metadata-Version: 2.1
Name: pytonik-agent
Version: 1.0.5
Summary: pytonik agent browser and OS module
Home-page: https://github.com/pytonik/pytonik_agent
Author: pytonik
Author-email: info@pytonik.com
Maintainer: Emmanuel Essien
Maintainer-email: emmamartinscm@gmail.com
License: Apache 2.0
Keywords: mvc,oop,module,framework,pytonik,agent,os
Platform: UNKNOWN
Classifier: Environment :: Console
Classifier: License :: OSI Approved :: MIT License
Classifier: Environment :: Web Environment
Classifier: Intended Audience :: End Users/Desktop
Classifier: Intended Audience :: Developers
Classifier: Intended Audience :: System Administrators
Classifier: License :: OSI Approved :: Python Software Foundation License
Classifier: Programming Language :: Python
Classifier: Topic :: Office/Business
Classifier: Intended Audience :: Developers
Classifier: License :: OSI Approved :: MIT License
Classifier: Operating System :: OS Independent
Classifier: Programming Language :: Python :: 2.7
Classifier: Programming Language :: Python :: 3
Classifier: Programming Language :: Python :: 3.4
Classifier: Programming Language :: Python :: 3.5
Classifier: Programming Language :: Python :: 3.6
Classifier: Programming Language :: Python :: 3.7
Classifier: Programming Language :: Python :: 3.8
Classifier: Programming Language :: Python
Requires-Python: >=2.7, >=3
